ZuozaiMatongShangxueSuanfaV11/README.md
ZuozaiMatongShangxueSuanfaV11/__init__.py
ZuozaiMatongShangxueSuanfaV11/__main__.py
ZuozaiMatongShangxueSuanfaV11/file.epub
ZuozaiMatongShangxueSuanfaV11/index.html
ZuozaiMatongShangxueSuanfaV11/css/__init__.py
ZuozaiMatongShangxueSuanfaV11/css/annotations.css
ZuozaiMatongShangxueSuanfaV11/css/main.css
ZuozaiMatongShangxueSuanfaV11/css/normalize.css
ZuozaiMatongShangxueSuanfaV11/css/popup.css
ZuozaiMatongShangxueSuanfaV11/font/__init__.py
ZuozaiMatongShangxueSuanfaV11/font/fontello.eot
ZuozaiMatongShangxueSuanfaV11/font/fontello.svg
ZuozaiMatongShangxueSuanfaV11/font/fontello.ttf
ZuozaiMatongShangxueSuanfaV11/font/fontello.woff
ZuozaiMatongShangxueSuanfaV11/img/__init__.py
ZuozaiMatongShangxueSuanfaV11/img/annotator-glyph-sprite.png
ZuozaiMatongShangxueSuanfaV11/img/annotator-icon-sprite.png
ZuozaiMatongShangxueSuanfaV11/img/apple-touch-icon.png
ZuozaiMatongShangxueSuanfaV11/img/cancelfullscreen.png
ZuozaiMatongShangxueSuanfaV11/img/close.png
ZuozaiMatongShangxueSuanfaV11/img/fullscreen.png
ZuozaiMatongShangxueSuanfaV11/img/loader.gif
ZuozaiMatongShangxueSuanfaV11/img/menu-icon.png
ZuozaiMatongShangxueSuanfaV11/img/save.png
ZuozaiMatongShangxueSuanfaV11/img/saved.png
ZuozaiMatongShangxueSuanfaV11/img/settings-s.png
ZuozaiMatongShangxueSuanfaV11/img/settings.png
ZuozaiMatongShangxueSuanfaV11/img/star.png
ZuozaiMatongShangxueSuanfaV11/js/__init__.py
ZuozaiMatongShangxueSuanfaV11/js/epub.js
ZuozaiMatongShangxueSuanfaV11/js/epub.min.js
ZuozaiMatongShangxueSuanfaV11/js/epub.min.map
ZuozaiMatongShangxueSuanfaV11/js/hooks.min.js
ZuozaiMatongShangxueSuanfaV11/js/hooks.min.map
ZuozaiMatongShangxueSuanfaV11/js/reader.js
ZuozaiMatongShangxueSuanfaV11/js/reader.js.map
ZuozaiMatongShangxueSuanfaV11/js/reader.min.js
ZuozaiMatongShangxueSuanfaV11/js/reader.min.map
ZuozaiMatongShangxueSuanfaV11/js/hooks/__init__.py
ZuozaiMatongShangxueSuanfaV11/js/hooks/extensions/__init__.py
ZuozaiMatongShangxueSuanfaV11/js/hooks/extensions/highlight.js
zuozai_matong_shangxue_suanfa_v1_1-2024.3.2.0.dist-info/METADATA
zuozai_matong_shangxue_suanfa_v1_1-2024.3.2.0.dist-info/WHEEL
zuozai_matong_shangxue_suanfa_v1_1-2024.3.2.0.dist-info/entry_points.txt
zuozai_matong_shangxue_suanfa_v1_1-2024.3.2.0.dist-info/top_level.txt
zuozai_matong_shangxue_suanfa_v1_1-2024.3.2.0.dist-info/RECORD
